netbox_dns/__init__.py
netbox_dns/admin.py
netbox_dns/api/nested_serializers.py
netbox_dns/api/serializers.py
netbox_dns/api/urls.py
netbox_dns/api/views.py
netbox_dns/apps.py
netbox_dns/fields/__init__.py
netbox_dns/fields/address.py
netbox_dns/fields/network.py
netbox_dns/filters/__init__.py
netbox_dns/filters/nameserver.py
netbox_dns/filters/record.py
netbox_dns/filters/view.py
netbox_dns/filters/zone.py
netbox_dns/forms/__init__.py
netbox_dns/forms/nameserver.py
netbox_dns/forms/record.py
netbox_dns/forms/view.py
netbox_dns/forms/zone.py
netbox_dns/graphql/__init__.py
netbox_dns/graphql/nameserver.py
netbox_dns/graphql/record.py
netbox_dns/graphql/schema.py
netbox_dns/graphql/view.py
netbox_dns/graphql/zone.py
netbox_dns/management/commands/cleanup_database.py
netbox_dns/management/commands/update_soa.py
netbox_dns/migrations/0001_initial.py
netbox_dns/migrations/0001_squashed_netbox_dns_0_15.py
netbox_dns/migrations/0002_zone_default_ttl.py
netbox_dns/migrations/0003_soa_managed_records.py
netbox_dns/migrations/0004_create_ptr_for_a_aaaa_records.py
netbox_dns/migrations/0005_update_ns_records.py
netbox_dns/migrations/0006_zone_soa_serial_auto.py
netbox_dns/migrations/0007_alter_zone_soa_serial_auto.py
netbox_dns/migrations/0008_zone_status_names.py
netbox_dns/migrations/0009_netbox32.py
netbox_dns/migrations/0010_update_soa_records.py
netbox_dns/migrations/0011_add_view_model.py
netbox_dns/migrations/0012_adjust_zone_and_record.py
netbox_dns/migrations/0013_add_nameserver_zone_record_description.py
netbox_dns/migrations/0014_add_view_description.py
netbox_dns/migrations/0015_add_record_status.py
netbox_dns/migrations/0016_cleanup_ptr_records.py
netbox_dns/migrations/0017_alter_record_ttl.py
netbox_dns/migrations/0018_zone_arpa_network.py
netbox_dns/migrations/0019_update_ns_ttl.py
netbox_dns/migrations/0020_netbox_3_4.py
netbox_dns/migrations/0021_record_ip_address.py
netbox_dns/migrations/0022_search.py
netbox_dns/migrations/__init__.py
netbox_dns/models.py
netbox_dns-0.17.0.dist-info/METADATA
netbox_dns-0.17.0.dist-info/WHEEL
netbox_dns-0.17.0.dist-info/LICENSE
netbox_dns-0.17.0.dist-info/RECORD
