Metadata-Version: 2.1
Name: netbox-dns
Version: 0.17.0
Summary: Netbox Dns is a netbox plugin for managing zone, nameserver and record inventory.
Home-page: https://github.com/auroraresearchlab/netbox-dns
License: MIT
Keywords: netbox,netbox-plugin,dns
Author: Aurora Research Lab
Author-email: info@auroraresearchlab.com
Requires-Python: >=3.8,<4.0
Classifier: License :: OSI Approved :: MIT License
Classifier: Programming Language :: Python :: 3
Classifier: Programming Language :: Python :: 3.8
Classifier: Programming Language :: Python :: 3.9
Classifier: Programming Language :: Python :: 3.10
Classifier: Programming Language :: Python :: 3.11
Requires-Dist: dnspython (>=2.2.1,<3.0.0)
Project-URL: Repository, https://github.com/auroraresearchlab/netbox-dns
